LICENSE
README.md
setup.py
tktk/MenuSet.py
tktk/StatusFrame.py
tktk/__init__.py
tktk.egg-info/PKG-INFO
tktk.egg-info/SOURCES.txt
tktk.egg-info/dependency_links.txt
tktk.egg-info/requires.txt
tktk.egg-info/top_level.txt
tktk.egg-info/zip-safe
tktk/base_enhance/ClockFrame.py
tktk/base_enhance/GifFrame.py
tktk/base_enhance/ListFrame.py
tktk/base_enhance/LogFrame.py
tktk/base_enhance/RollingLabel.py
tktk/base_enhance/TableFrame.py
tktk/base_enhance/TestStateFrame.py
tktk/base_enhance/TipShow.py
tktk/base_enhance/__init__.py