Metadata-Version: 2.1
Name: tktk
Version: 0.4.7
Summary: tkinter的增强控件,将tkinter的基础控件进行封装,给予更强大的控件功能,所有控件继承于LabelFrame进行封装,使用方法和普通控件没什么区别;
Home-page: https://gitee.com/w-8/tktk
Author: bili:凿寂
Author-email: mdzzdyxc@163.com
License: MIT
Platform: UNKNOWN
Classifier: Programming Language :: Python :: 3
Classifier: License :: OSI Approved :: MIT License
Classifier: Operating System :: OS Independent
License-File: LICENSE
